itkwasm_elastix_emscripten/__init__.py
itkwasm_elastix_emscripten/_version.py
itkwasm_elastix_emscripten/default_parameter_map_async.py
itkwasm_elastix_emscripten/elastix_async.py
itkwasm_elastix_emscripten/js_package.py
itkwasm_elastix_emscripten/read_parameter_files_async.py
itkwasm_elastix_emscripten/transformix_async.py
itkwasm_elastix_emscripten/write_parameter_files_async.py
itkwasm_elastix_emscripten-1.0.2.dist-info/METADATA
itkwasm_elastix_emscripten-1.0.2.dist-info/WHEEL
itkwasm_elastix_emscripten-1.0.2.dist-info/RECORD
